nest_asyncio.py
nest_asyncio_adv-1.7.0b0.dist-info/LICENSE
nest_asyncio_adv-1.7.0b0.dist-info/METADATA
nest_asyncio_adv-1.7.0b0.dist-info/WHEEL
nest_asyncio_adv-1.7.0b0.dist-info/top_level.txt
nest_asyncio_adv-1.7.0b0.dist-info/RECORD
