Metadata-Version: 2.1
Name: nest_asyncio_adv
Version: 1.7.0b0
Summary: Patch asyncio to allow nested event loops
Home-page: https://github.com/ufoptg/asyncNestADV
Author: ufoptg
Author-email: de.wit@gmail.com
License: GNUv3
Keywords: asyncio,nested,eventloop
Classifier: Development Status :: 5 - Production/Stable
Classifier: Intended Audience :: Developers
Classifier: License :: OSI Approved :: BSD License
Classifier: Programming Language :: Python :: 3.5
Classifier: Programming Language :: Python :: 3.6
Classifier: Programming Language :: Python :: 3.7
Classifier: Programming Language :: Python :: 3.8
Classifier: Programming Language :: Python :: 3.9
Classifier: Programming Language :: Python :: 3.10
Classifier: Programming Language :: Python :: 3.11
Classifier: Programming Language :: Python :: 3.12
Classifier: Programming Language :: Python :: 3 :: Only
Classifier: Framework :: AsyncIO
Requires-Python: >=3.5
License-File: LICENSE
